README.md
setup.py
ICARUS/__init__.py
IcarusApi.egg-info/PKG-INFO
IcarusApi.egg-info/SOURCES.txt
IcarusApi.egg-info/dependency_links.txt
IcarusApi.egg-info/top_level.txt
base/__init__.py
cli/__init__.py
cmds/__init__.py
coding/__init__.py
docker/__init__.py
files/__init__.py
fofa/__init__.py
net/__init__.py
strings/__init__.py
utils/__init__.py
vault/__init__.py
windows/__init__.py