Metadata-Version: 2.1
Name: IcarusApi
Version: 0.1.95
Summary: Icarus Api
Home-page: http://icarus.n0p3.cn
Author: N0P3
Author-email: n0p3@qq.com
License: UNKNOWN
Platform: UNKNOWN
